[{"slug":"20210212-use-log4brains-to-manage-the-adrs","package":null,"title":"Use Log4brains to manage the ADRs","status":"accepted","creationDate":"2021-05-24T01:31:13.000Z","publicationDate":"2021-02-12T07:59:59.000Z"},{"slug":"20210212-use-markdown-architectural-decision-records","package":null,"title":"Use Markdown Architectural Decision Records","status":"accepted","creationDate":"2021-05-24T01:31:13.000Z","publicationDate":"2021-02-12T07:59:59.000Z"},{"slug":"20210212-add-build-notifications","package":null,"title":"Add build notifications","status":"proposed","creationDate":"2021-05-24T01:31:13.000Z","publicationDate":"2021-02-13T07:59:59.000Z"},{"slug":"20210428-use-kubernetes","package":null,"title":"Use kubernetes","status":"draft","creationDate":"2021-05-24T01:31:13.000Z","publicationDate":null}]